virtualenv_seedhelper.py
virtualenv_seedhelper-0.0.1.dist-info/LICENSE.txt
virtualenv_seedhelper-0.0.1.dist-info/METADATA
virtualenv_seedhelper-0.0.1.dist-info/WHEEL
virtualenv_seedhelper-0.0.1.dist-info/entry_points.txt
virtualenv_seedhelper-0.0.1.dist-info/top_level.txt
virtualenv_seedhelper-0.0.1.dist-info/RECORD
