Metadata-Version: 2.1
Name: virtualenv-seedhelper
Version: 0.0.1
Summary: A virtualenv seeder to seed wheels from a folder
Author-email: Thomas Gilgenast <thomasgilgenast@gmail.com>
Project-URL: repository, https://github.com/sclabs/virtualenv-seedhelper
Requires-Python: >=3.7
License-File: LICENSE.txt
Requires-Dist: fire
Requires-Dist: platformdirs
Requires-Dist: virtualenv
Provides-Extra: dev
Requires-Dist: tox-extras[lint,test,type] ; extra == 'dev'
Provides-Extra: lint
Requires-Dist: black ==23.3.0 ; extra == 'lint'
Requires-Dist: ruff ==0.0.262 ; extra == 'lint'
Provides-Extra: test
Requires-Dist: pytest ==7.3.1 ; extra == 'test'
Requires-Dist: tox ==4.4.12 ; extra == 'test'
Requires-Dist: tox-extras ==0.0.1 ; extra == 'test'
Provides-Extra: type
Requires-Dist: mypy ==1.2.0 ; extra == 'type'
